errr/__init__.py
errr/exception.py
errr/tree.py
errr-1.2.2.dist-info/licenses/LICENSE
errr-1.2.2.dist-info/WHEEL
errr-1.2.2.dist-info/METADATA
errr-1.2.2.dist-info/RECORD
