Metadata-Version: 2.4
Name: errr
Version: 1.2.2
Summary: Elegant detailed Python exceptions.
Author-email: Robin De Schepper <robin@alexandria.sc>
License-Expression: MIT
License-File: LICENSE
Project-URL: Home, https://alexandria.sc
